data_enricher/__init__.py
data_enricher/comparison.py
data_enricher/models/__init__.py
data_enricher/models/kde_models.py
data_enricher/models/submodels.py
data_enricher/models/vae_models.py
data_enricher/utils/__init__.py
data_enricher/utils/kde_utils.py
data_enricher/utils/vae_utils.py
data_enricher-0.1.3.dist-info/LICENSE
data_enricher-0.1.3.dist-info/METADATA
data_enricher-0.1.3.dist-info/WHEEL
data_enricher-0.1.3.dist-info/top_level.txt
data_enricher-0.1.3.dist-info/RECORD
