Metadata-Version: 2.1
Name: data-enricher
Version: 0.1.3
Summary: A Python package for enriching data by probabilistic modelling.
Author-email: Kutay Bölat <k.bolat@tudelft.nl>
License: MIT License
Project-URL: Repository, https://github.com/kabolat/data_enricher
Classifier: License :: OSI Approved :: MIT License
Classifier: Operating System :: OS Independent
Classifier: Topic :: Scientific/Engineering
Classifier: Intended Audience :: Science/Research
Classifier: Programming Language :: Python :: 3
Requires-Python: <=3.10,>=3.9
License-File: LICENSE
Requires-Dist: torch >=2.0.0
Requires-Dist: scipy >=1.8.1
